{"id":1011181,"date":[{"year":1995,"month":10,"day":26}],"page":"11","source":"","region":"","masthead":"市场与消费","special_issue":"","column":"","genre":"","count":"150","ytitle":"","mtitle":"日前，上海市技术监督局专门为上海海象电光源实业有限公司生产的海象、海龙牌全电子式节能灯召开推广会议","ftitle":"","authors":[],"text":[{"type":"paragraph","text":"<IMG alt=请插入10号盘，按F5键刷新后显示本插图！ src=\"D:\\inset\\1995\\10\\95aq110501.JPG\">"},{"type":"paragraph","text":"<FONT class=imgaut>明亮</FONT>"},{"type":"paragraph","text":"<FONT class=imgsm>日前，上海市技术监督局专门为上海海象电光源实业有限公司生产的海象、海龙牌全电子式节能灯召开推广会议。该产品的使用寿命可达8000小时，超过了目前市场上销售的国产节能灯的使用寿命。"},{"type":"paragraph","text":"明亮　文</FONT>"}]}