{"id":1086044,"date":[{"year":1997,"month":4,"day":10}],"page":"2","source":"本报","region":"","masthead":"经济政法·社会新闻","special_issue":"","column":"","genre":"","count":"656","ytitle":"市委向党外人士通报反腐倡廉工作","mtitle":"上海四年来共立案查处　领导干部违纪案七千件","ftitle":"","authors":["宋琤","姚柏生"],"text":[{"type":"paragraph","text":"本报讯　(记者宋琤　姚柏生)　中共上海市委昨天在市委统战部召开本市各民主党派、工商联负责人和无党派代表人士座谈会，通报本市党风廉政建设工作情况，听取党外人士对本市反腐倡廉工作的建议与意见。市委常委、市纪委书记张惠新到会通报情况，市委统战部部长王生洪主持会议。"},{"type":"paragraph","text":"张惠新向与会人士介绍了自1993年以来，在市委的高度重视和统一领导下，在社会各界和全市人民的积极参与和支持下，本市反腐败斗争所取得的成绩。从1993年8月到1996年四年间，全市纪检监察机关共立案查处领导干部违纪案件7081件，给予党纪政纪处分6016人，受到撤销党内职务以上重处分的有2928人，其中被开除党籍2279人；全市检察机关立案查处贪污受贿等经济案件5824件，其中大案要案4605件，追缴赃款近5亿元，挽回经济损失2.86亿元。张惠新在会上还分析了近几年来本市反腐败斗争的主要特点和目前还存在的问题，指出反腐败斗争任务仍然十分艰巨，在新的一年里要继续加大工作力度，狠抓落实，务求实效。"},{"type":"paragraph","text":"与会人士在听取了情况介绍后，在发言中对本市近年来反腐败工作所取得的成绩给予了充分肯定。同时指出，目前反腐败斗争形势依然严峻，对存在的问题不能低估。"},{"type":"paragraph","text":"市政协主席陈铁迪和本市各民主党派、工商联负责人、无党派代表人士厉无畏、陈铭珊、刘恒椽、郑励志、郭秀珍、翁曙冠、濮之珍、俞云波、张重超、罗冠宗，以及市委统战部副部长陶人观、吴汉民、钟燕群、孙金富等60余人参加了座谈会。"}]}