{"id":314761,"date":[{"year":1954,"month":11,"day":19}],"page":"2","source":"","region":"","masthead":"","special_issue":"","column":"在祖国辽阔的土地上","genre":"","count":"239","ytitle":"","mtitle":"南京仪器厂生产显微镜","ftitle":"","authors":[],"text":[{"type":"paragraph","text":"国营南京科学仪器厂职工正努力为学校制造大批六百倍的生物显微镜。现在金属零件的加工有的已完成了，显微镜目镜升降筒上已经刻上了“国营南京科学仪器厂”的字样；经过车工克服了重重困难提前完成的固定板和转动板，现在已在女工的手上进行部件装配了。"},{"type":"paragraph","text":"生物显微镜是精密的科学仪器，这是科学仪器厂从来没有制造过的。当该厂试制的时候，有些人不相信在很短的时间内就能生产，但是该厂职工却以两个月的时间顺利地完成了试制和小批生产的任务，目前就要进行大批生产的装配了。"}]}