{"id":430323,"date":[{"year":1962,"month":5,"day":8}],"page":"4","source":"","region":"","masthead":"","special_issue":"笔会","column":"读者中来","genre":"","count":"367","ytitle":"","mtitle":"向放映员进一言","ftitle":"","authors":["李鑫元"],"text":[{"type":"paragraph","text":"每当我看到一部优秀影片时，除了感激编、导、演等创作人员的辛勤劳动外，还想到常被“影迷”们忽视的幕后英雄——放映员的一份功劳!"},{"type":"paragraph","text":"好的放映员的接片，总是显得和谐、完整、协调，毫无“接”的痕迹。但是，有时也发生令人不满的事情。一部好的影片，就因为放映效果不好，使人感到索然无味。前一时期到某影院重看《革命家庭》，放映效果很差，不是断片、“跳格”，就是画面暗淡模糊，音乐节奏断续无常，非常难听。因此初次看片时留给我的好印象一下被冲淡了，更遗憾的是一些节骨眼的对话、动作，由于断片、“跳格”，被“略”了过去，使人产生不理解的现象。为此我要向放映员同志进一言，为了把放映质量提高，是不是可以从这三方面着手:(1)提高放映技术；(2)充分做好映前检查准备工作；(8)学习电影艺术基本知识，如镜头组接、“蒙太奇”等等。"},{"type":"paragraph","text":"李鑫元"}]}