{"id":470305,"date":[{"year":1965,"month":10,"day":11}],"page":"3","source":"新华社","region":"北京","masthead":"","special_issue":"","column":"","genre":"","count":"246","ytitle":"","mtitle":"南越解放军神出鬼没伏击敌人 美军车队在西贡附近受到重创","ftitle":"","authors":[],"text":[{"type":"paragraph","text":"新华社北京10日电　西贡消息:越南南方解放军八日晚上在西贡附近地区神出鬼没地伏击了一支由二十辆卡车组成的美军车队，车上载运的是美国陆军第一步兵师的侵略军。"},{"type":"paragraph","text":"据合众国际社报道，美国军方发言人说，在解放军伏击前仅仅三十分钟，一排美军刚刚“扫荡”过出事地点，“当时没有发现任何可疑的东西。”但是，当这个车队沿西贡东北三十英里不远的一条公路行进的时候，地雷突然爆炸了，解放军还用迫击炮和自动武器袭击这个车队。使美军第一步兵师第二旅一个连的士兵遭到伤亡。"}]}