{"id":993581,"date":[{"year":1995,"month":6,"day":21}],"page":"11","source":"","region":"","masthead":"海外瞭望","special_issue":"","column":"","genre":"","count":"565","ytitle":"美国法律界的一件怪事","mtitle":"毒品巨头成为法院高参","ftitle":"","authors":[],"text":[{"type":"paragraph","text":"向标榜法度严明的美国常有怪事发生。最近一期的美国《国家咨询者》杂志披露了一件事，折射出美国法律中光怪陆离的一面。"},{"type":"paragraph","text":"哈维·普拉格曾经是国际毒品集团的头面人物，80年代他策划了一次毒品走私行动，竟然把总量达11吨，价值2千万美元的大麻偷运进缅因州。阴谋败露后，他仓皇逃往欧洲，3年后他向警方自首，令人不可思议的是，数额如此巨大，程度如此严重，在美国历史上也属罕见的贩毒罪行却被从轻发落。他没有坐过一天班房，对他的“惩罚”是，让他在自己家里照顾爱滋病人。这倒给了普拉格天赐良机，在此期间，他潜心攻读法律学，结果成绩相当优异。"},{"type":"paragraph","text":"去年8月，缅因州高等法院霍华德·达纳法官鉴于其“学业优秀”将其作为“人才”录用在州高等法院里，从事法律研究，为法官的决议出谋划策，这在州衙里是一个令人羡慕的职务。"},{"type":"paragraph","text":"此举令当地法律界人士大为震惊，人们纷纷投书州法学界要人要求撤换普拉格。缅因州检举人协会主席柯洛克指出，“在公众心目中，普拉格参与法律事务会给法庭的判决抹黑。”缅因州警方人士说得更为直截了当:“这是给正义制度扇了一记耳光!”"},{"type":"paragraph","text":"然而达纳法官坚持认为“普拉格才华横溢，应该给他第二次机会。”对此有人反唇相讥“他的确有‘才华’，要知道他做了国际毒品集团8年到10年的当家人，如果是笨蛋，能坐这么久吗?”"},{"type":"paragraph","text":"燕镌"},{"type":"paragraph","text":"<IMG alt=请插入10号盘，按F5键刷新后显示本插图！ src=\"D:\\inset\\1995\\06\\956L110601.JPG\">"},{"type":"paragraph","text":"<FONT class=imgaut>燕镌</FONT>"}]}