{"id":119536,"date":[{"year":1946,"month":11,"day":2}],"page":"2","source":"路透社,法国新闻社","region":"华盛顿,伦敦","masthead":"","special_issue":"","column":"","genre":"","count":"875","ytitle":"本月外长会议时","mtitle":"将讨论对德和约","ftitle":"贝尔纳斯称和约草案拟定前　四强对主要问题必先获协议","authors":[],"text":[{"type":"paragraph","text":"【路透社华盛顿三十一日电】国务卿贝尔纳斯，今日招待记者称:渠将于下月初举行之外长会议，任命专任代表研究德和约之整个问题。美国于讨论德国之经济统一或赔款等问题时，当坚决以波茨坦协定为根据，并将请其他政府亦受该协定之拘束。外长会议至少须至十一月卅日始能讨论德国问题，至彼时渠犹不能确定是否得有任何有效之收获。渠已令德境美军政府首长克莱将军及政治顾问墨菲大使于十一月二十日返美一行，与其一谈，以为四强审查德国和约之准备，贝卿谓:四强外长已同意在讨论德国问题前，先解决义罗匈保芬五国和约，俟解决后始能决定是否得在联大结束前完成德国问题之适当讨论，或是否宜于两三星期以后再在欧洲定期开会。贝卿未曾透露渠已否拟具德国和约草案，但曰:渠将建议由每一占领国任命专任代表，以共同拟具对德和约之草案，此项办法之施行，必须由四强先就主要问题如疆界问题等成立协议。外长会议于讨论德国问题时，更必须审查占领之困难问题。关于本周初所传德境之苏当局对于统一德国经济之完成已有重大进步之说，贝卿谓如果西方盟国准许苏联以其占领区内之德国生产作为赔偿，则苏当局或能同意此一行动，美国关于此事，决以波茨坦协定为据云"},{"type":"paragraph","text":"【法国新闻社华盛顿卅一日电】美国务卿贝尔纳斯顷向报界谈称:四国外长在纽约举行会议，对于德国问题若不能获致任何进展，成立协议，则余将拒绝参加任何新的国际会议，惟四国外长欲在十一月廿日以前，解决德国问题，殆不可能云。"},{"type":"paragraph","text":"【法国新闻社伦敦卅一日电】此间消息灵通人士顷谈称:英苏两国对于德国问题，现似可能成立协定，盟国管制德国委员会英苏两国代表曾进行谈判。结果双方对于德国问题之各方面已获得密切谅解。惟英苏两国对于德国问题成立协定之最大困难。乃在经济问题，英国谴责苏联利用德国经济专谋苏联本身之利益，此在英国，则消耗大批金钱以维持德国西部人民之生计。苏联如坚持此项政策而不变，则四国占领区实行合并之结果，徒然增加英国之负担而已。苏联遵照波次坦协定之规定，在德国收支不能平衡期间，实不能以德国现行生产作为赔偿云。"}]}