{"id":116530,"date":[{"year":1946,"month":10,"day":14}],"page":"1","source":"本报,合众社","region":"天津","masthead":"","special_issue":"","column":"","genre":"","count":"339","ytitle":"","mtitle":"研讨“扫荡”计划","ftitle":"陈诚曾飞归绥晤傅作义　返平时并空中视察张垣","authors":[],"text":[{"type":"paragraph","text":"【本报天津十三日专电】　陈总长抵平后，十二日曾赴归绥与傅作义研讨“扫荡”计划，中途并在张垣上空视察，当晚返平，在平军事首长，曾在勤政殿设宴欢宴陈氏，各人携眷参加。(金)"},{"type":"paragraph","text":"【合众社北平十三日电】据息:陈诚总参谋长昨晨飞往归绥与傅作义将军商议后，飞归时途经张垣在上空巡视。"},{"type":"paragraph","text":"张垣飞机场，破坏甚重，陈氏之飞机未能降陆，只能低飞，颇旋张垣上空，调查损失情形。据新生报称:中共军撤退时，破坏甚烈，当陈氏空中巡视之间，城中犹有火烟上升，大街上仍有火烧，火车站及水塔完全毁坏，城外二飞机场皆不堪应用。须经二三日修理后，方可使用。此间接获张垣国军来电称:国军司令官最先入城者，系董其武将军及骑兵司令陈方(译音)将军董其武将军现暂为张垣警备司令。"}]}