{"id":1040504,"date":[{"year":1996,"month":5,"day":24}],"page":"11","source":"","region":"","masthead":"海外瞭望","special_issue":"消费导向专栏","column":"","genre":"","count":"212","ytitle":"","mtitle":"上海市沪东中学建校四十周年校庆启事","ftitle":"","authors":[],"text":[{"type":"paragraph","text":"本校初定于96年11月举行建校40周年庆典，凡历届校友(含原东昌二中的校友)请将本人简况(包括姓名、入学及毕业时间、现工作单位、职务、通讯地址、联系电话、邮编等)函告校庆筹备组，并请海内外校友相互转告。"},{"type":"paragraph","text":"汪大方校长偕历任校长严华业等率全体员工向老同仁、老校友致意!"},{"type":"paragraph","text":"校址:浦东大道830号联系电话:58310316或58318123"},{"type":"paragraph","text":"邮编:200120"},{"type":"paragraph","text":"上海市沪东中学校庆筹备组"},{"type":"paragraph","text":"1996、5"}]}