{"id":1214135,"date":[{"year":1999,"month":8,"day":20}],"page":"3","source":"本报","region":"","masthead":"文化新闻","special_issue":"","column":"","genre":"","count":"707","ytitle":"煌煌3000余卷隆重推出","mtitle":"《全宋诗》完璧面世","ftitle":"","authors":["邢晓芳","曹静"],"text":[{"type":"paragraph","text":"本报讯(记者邢晓芳实习生曹静)　由北京大学古典文献研究所编写的72册《全宋诗》日前全部出齐，由北京大学出版社隆重推出。"},{"type":"paragraph","text":"唐诗与宋诗，历来被称为我国古代诗歌的两座高峰。唐诗已有《全唐诗》为其总汇，《外编》为其补遗，而宋诗尚无一代总集，《全宋诗》之编撰实为中国诗歌史和中国文学史研究以及弘扬优秀传统文化所急需。为此，早在1986年，《全宋诗》便被列为教育部全国高校古籍整理研究工作重点科研项目，1992年又被列入国务院古籍整理规划“八五”重点图书。自1991年开始，《全宋诗》共72册由北京大学出版社陆续出版，历时8年终于完成了这一浩大的工程，《全宋诗》从而与《全唐诗》一起成为我国出版史上的双璧。"},{"type":"paragraph","text":"作为大型诗歌总集，《全宋诗》分72册3785卷、共3734万字，收录诗人8900余名，其中成集作家600余人，无诗集传世的作者8000余人。《全宋诗》考订比勘的规模远远超过《全唐诗》，其整理、编撰和出版是一项难度很大，内容繁复的学术研究和组织工作。傅璇琼、孙钦善、倪其心、陈新、许逸民率领的北大古文献研究所投入了大量精力，作了许多认真细致的工作。本书编次，以作者生年先后为序，所收各家诗均详注出处，8900余诗人均撰明小传，在诗人小传之后还附有专段版本说明。在校勘方面，考察了各种版本源流，选择善本、足本为底本，确定有价值的本子为参校本，然后进行比勘对校，主校是非，酌校异同，以简明校语随文夹注，极具学术价值。同时，《全宋诗》还注重吸收当代的研究成果，其编校质量和出版价值，得到了学术界程千帆、邓广铭多位知名学者的肯定。据悉，该书已人围参加今年的国家图书奖评选。"}]}