{"id":974107,"date":[{"year":1995,"month":2,"day":8}],"page":"6","source":"本报","region":"","masthead":"体育新闻","special_issue":"","column":"","genre":"","count":"323","ytitle":"两路征战欧洲　一路过关斩将","mtitle":"杨绍琦肖爱华扬威剑坛","ftitle":"","authors":["季安之"],"text":[{"type":"paragraph","text":"本报讯　(记者季安之)中国女剑客近日分两路征战欧洲，取得了一连串的好成绩。"},{"type":"paragraph","text":"中国选手杨绍琦二月四日至五日在法国圣慕尔举行的第七届世界女子重剑A级赛上，一路过关斩将，夺得冠军，这是中国选手在女子重剑项目上取得的最好成绩。"},{"type":"paragraph","text":"同一时间在法国圣但尼-德洛泰尔举行的法国第六届国际女子花剑邀请赛上，由肖爱华、梁军、孟洁和叶琳组成的中国队获团体冠军，肖爱华还获得个人第一名，梁军和孟洁并列第三。"},{"type":"paragraph","text":"肖爱华还在一周前于德国哥平根举行的世界杯女花A级赛上夺得第二名，这也是继十年前栾菊杰取得这一传统比赛冠军后中国选手取得的第二个好成绩。"},{"type":"paragraph","text":"世界杯A级赛是国际剑联主办的重大击剑赛事，其规格仅次于奥运会和世界击剑锦标赛。"}]}