{"id":186265,"date":[{"year":1950,"month":5,"day":14}],"page":"5","source":"","region":"","masthead":"","special_issue":"","column":"","genre":"","count":"364","ytitle":"","mtitle":"夏令防疫新开篇 无病无痛乐陶陶","ftitle":"","authors":["周行"],"text":[{"type":"paragraph","text":"周行"},{"type":"paragraph","text":"烈日炎炎似火烧，夏令防疫最紧要。传染霍乱须防止，饮食生冷要把祸招。有一个张大娘自以为身体好，喝水从来不肯烧。汗流浃背口干燥，他是一口口尽向嘴里浇。吃的时候真爽快，那晓得病菌入肚起祸苗。刹时间呕吐腹泻无止歇，四肢麻木痛难熬。急忙忙送入医院去，才得保全命一条。再有那贪吃消闲的王阿大，摊头小贩把闲食消。早起吃冷面，下午白糖糕，吃了黄金瓜，又吃烂香蕉；那知道摊头的瓜菓用冷水浇，那知道苍蝇传染留细胞；那知道霍乱病菌在肚里闹，在他肠胃之间一团糟。平常不肯防疾病，霍乱来时命难逃。因此上预防病疫须注意，未雨绸缪要记牢。防疫针，不可少，省了金钱又省治疗。更其是小小儿女无知识，家长责任更重要。注意卫生第一件，里弄清洁要记牢。污水切忌随地倒，瓜皮不能到处抛。人生首须有康健，无病无痛乐陶陶；预防注射最紧要。"}]}