{"id":203236,"date":[{"year":1950,"month":11,"day":10}],"page":"7","source":"","region":"","masthead":"","special_issue":"新妇女","column":"妇女们动员起来!为抗美援朝·保家卫国而斗争,每周漫谈","genre":"","count":"472","ytitle":"","mtitle":"寒衣运动和抗美运动","ftitle":"","authors":[],"text":[{"type":"paragraph","text":"姊妹们现在正为灾民征募寒衣，但我们要想想，我们怎么来这许多灾民呢?"},{"type":"paragraph","text":"想想吧，我们打败日本鬼子已经五个年头了，如果能够展开建设工作，老早就‘国泰民安’，又何至于遍地灾鸿呢!请看苏联吧，它在战时所受损失要比我们大得多，但是它在战后，能够即时展开一个五年计划；到现在，国内所受战争的损失不但已经弥补，而且人民生活水准已经超过战前了。"},{"type":"paragraph","text":"但我们为什么不能像苏联这样呢?这就是由于美国帝国主义者从中作梗!"},{"type":"paragraph","text":"想想，抗日战争刚结束，美帝就大帮蒋匪帮的忙，把剩余的军火，全部廉价卖给它，又替它运兵，替它练兵；结果我们中国在八年战争之后，还来不及喘一口气，就又接着展开了一个内战——美蒋联合向中国人民进攻。中国人民奋起抗击，又打了三年才把他们赶出大陆。但到现在匪帮躲在台湾继续作恶，美帝又从朝鲜向我们挑衅，以至于直到今天，我们还不能休养生息。"},{"type":"paragraph","text":"这一连串战争，无尽的苦难日子，可说都是美帝一手造成的。所以我们的寒衣运动必须与抗美运动结合起来，只有打败美帝的挑衅，我们才能消灭灾难，我们才能过好日子。(木)"}]}