{"id":218477,"date":[{"year":1951,"month":3,"day":14}],"page":"3","source":"","region":"","masthead":"","special_issue":"","column":"长街短巷","genre":"","count":"260","ytitle":"","mtitle":"小型会议","ftitle":"","authors":[],"text":[{"type":"paragraph","text":"延安中路明德里有三十七户人家，过去从不出席里弄里任何会议，该里福利会工作同志最近特分头拜访、恳谈，前后历时七、八天。前天晚上终于有十一位出席会议。会上从抗美援朝、反对美国武装日本，一直谈到居民福利。大家谈的津津有味，都说这样的小型会议，蛮有意思。保证以后开会必到。"},{"type":"paragraph","text":"嵩山区兰声里，老上海差不多都知道，是一个情况复杂的坏里弄。在里内普遍混迹着烟子叶、黄牛、流氓等辈。大家把它叫成“烂生梨”。但是解放以来，一切都改变了，福利会搞起来，冬防队又成立，修路，装路灯；坏人也改好了。现在，兰声里就不再是“烂生梨”了。"}]}