{"id":861604,"date":[{"year":1992,"month":3,"day":6}],"page":"1","source":"本报","region":"南京","masthead":"","special_issue":"","column":"","genre":"","count":"271","ytitle":"","mtitle":"道是“无锡”却有锡","ftitle":"太湖地区将成为新的锡矿基地","authors":["顾龙友"],"text":[{"type":"paragraph","text":"本报南京专讯　江苏省地质矿产局地质找矿获重大发现:太湖地区可望成为我国新的锡矿资源基地。这一重要发现，一改无锡无“锡”的说法。"},{"type":"paragraph","text":"锡矿是江苏省的空白矿种。在全省10万多平方公里的面积内寻找独立的锡矿床，是地质工作者30多年来孜孜以求的事。近年来，江苏省地质矿产局通过区域地球化学探矿和综合地质研究，已在太湖地区发现了一批锡矿点。其中，东山锡矿点的含锡品位0.62%，西山锡矿点的含锡最高品位为0.91%。"},{"type":"paragraph","text":"从发展来看，苏州、无锡地区有可能划入我国著名的四大成锡区之一的扬子准地台锡成矿区中。　(顾龙友)"}]}