{"id":1208980,"date":[{"year":1999,"month":7,"day":14}],"page":"2","source":"本报","region":"","masthead":"综合新闻","special_issue":"","column":"","genre":"","count":"307","ytitle":"","mtitle":"治安“大扫除”　黄赌是重点","ftitle":"本市夏季治安“严打”整治斗争进展顺利","authors":["陆炎"],"text":[{"type":"paragraph","text":"本报讯　(记者陆炎)入夏以来，上海警方治安力量针对夏季赌博、卖淫嫖娼活动多发的特点，以“除尘务尽”的精神开展了多次“严打”整治“大扫除”行动，狠狠打击了此类违法犯罪活动。"},{"type":"paragraph","text":"在今夏治安“大扫除”中，警方治安部门将打击锋芒直指赌博场所，7月1日以来，全市共查获涉赌案件250余起，抓获赌徒1300余名。警方还查处卖淫嫖娼案件百余起，抓获对象320余人。同时通过设卡布控，扼制外省市淫秽音像制品的流入。"},{"type":"paragraph","text":"据市公安局治安总队负责人透露，下阶段除了继续加强行业场所的查禁整治外，将重点开展打击教唆流浪少儿违法犯罪活动，及打击制贩假文凭、假证件的违法犯罪活动。"}]}