{"id":1197579,"date":[{"year":1999,"month":4,"day":20}],"page":"11","source":"羊城晚报","region":"","masthead":"新闻视窗","special_issue":"新闻视窗(文汇信息中心)","column":"","genre":"","count":"346","ytitle":"","mtitle":"建幢新楼颂母爱","ftitle":"","authors":["邓勃"],"text":[{"type":"paragraph","text":"羊城晚报报道(邓勃)20年来含辛茹苦收养600个残病婴儿的劳秀玉，她和孩子们的新家——一栋三层小洋楼18日在广东雷州市雷城镇破土动工了。"},{"type":"paragraph","text":"上月27日，本报刊登《一个女人和600个孩子》一文后引起强烈反响，故事也感动了广东凤铝铝型材厂的老总和员工们，他们当即决定集全厂之力，为劳秀玉建一栋三层小洋楼的新家，同时让她的“孩子们”读上书，还这个伟大母亲一个心愿。"},{"type":"paragraph","text":"新家破土动工之前，“凤铝”员工还将劳秀玉和她的两个“孩子”接到南海和广州，陪他们玩个痛快。当晚接到南海时，劳秀玉和她的孩子们吃上了他们今年的第一顿米饭。“凤铝”老总吴小源说:“我们中有不少人夜夜笙歌，但一个伟大的母亲20年来几乎天天喝粥，拉扯大600个孩子——我们的社会应该帮助这样的母亲，应该颂扬这样的母亲。”"},{"type":"paragraph","text":"<IMG alt=请插入12号盘，按F5键刷新后显示本插图！ src=\"D:\\inset\\1999\\04\\994k111901.JPG\">"}]}