{"id":1197471,"date":[{"year":1999,"month":4,"day":20}],"page":"4","source":"新华社","region":"莫斯科","masthead":"国际新闻","special_issue":"","column":"北约空袭南联盟第27天","genre":"","count":"718","ytitle":"俄外长阐述和平解决南问题基本原则","mtitle":"指责北约对南采取“焦土战术”","ftitle":"叶利钦说俄不允许美国将南置于其“保护之下”","authors":["张铁柱"],"text":[{"type":"paragraph","text":"据新华社莫斯科4月19日电　俄罗斯外交部长伊万诺夫19日全面阐述了俄罗斯关于和平解决南斯拉夫问题的基本原则，并呼吁联合国就此发挥重要作用。"},{"type":"paragraph","text":"伊万诺夫说这些基本原则包括:立即在南境内停止包括“暴力与镇压”在内的一切军事行动，在从南联盟周边国家撤走北约进攻性部队的同时从科索沃撤出多余的南军队和警察部队；保证所有难民安全返回家园，为国际人道主义组织发挥职能创造条件；恢复南联盟领导人与科索沃阿族领导人在完全尊重南联盟国家主权和领土完整的条件下给科索沃以广泛自治地位问题而进行的政治谈判；推动包括科索沃在内的整个南联盟的经济重建工作。"},{"type":"paragraph","text":"伊万诺夫还强烈指责北约军队对南联盟采取“焦土战术”。他认为，北约正在制定对南联盟发动地面行动的几种方案。这些方案包括从部分占领科索沃并对其实行军事托管到占领南全境并进而将其肢解为数个小国的计划。他说，为了实施后一种方案，北约军队目前实际上已开始对南联盟采取“把一切统统变为沙漠”的野蛮的“焦土战术”。"},{"type":"paragraph","text":"据新华社4月19日电(记者　张铁柱)　俄罗斯总统叶利钦19日说，俄罗斯不能允许美国将南斯拉夫置于其“保护之下”。"},{"type":"paragraph","text":"叶利钦当天在克里姆林宫会见俄主要新闻媒体负责人时指出，美国总统克林顿试图让南联盟总统米洛舍维奇投降，并试图将整个南斯拉夫置于美国的“保护之下”，这是俄罗斯所不能允许的，因为对俄来说“巴尔干地区具有非常重要的战略地位”。"},{"type":"paragraph","text":"<IMG alt=请插入12号盘，按F5键刷新后显示本插图！ src=\"D:\\inset\\1999\\04\\994k040501.JPG\">"},{"type":"paragraph","text":"<FONT class=imgaut>义高潮</FONT>"},{"type":"paragraph","text":"<FONT class=imgsm>4月18日，20对南联盟青年男女在首都贝尔格莱德举行了集体婚礼。图为新人们在婚礼后到点心店领取结婚蛋糕。"},{"type":"paragraph","text":"新华社记者　义高潮摄(传真照片)</FONT>"}]}