{"id":835873,"date":[{"year":1991,"month":3,"day":26}],"page":"2","source":"本报","region":"","masthead":"综合新闻","special_issue":"","column":"","genre":"","count":"376","ytitle":"展出本市企业生产的两万多种产品","mtitle":"“四新”消费品博览会今开幕","ftitle":"","authors":[],"text":[{"type":"paragraph","text":"本报讯　上海市工业“四新”消费品博览会今天在上海展览中心开幕，展出本市近2000家企业生产的两万多种产品，其中“四新”名特优产品占70%，可供货源总额达35亿元，展示了本市工业系统产品升级换代的水平和产品结构调整的成果。"},{"type":"paragraph","text":"这个博览会由市经委主办，展示了各种新产品、新品种、新花色、新包装。上海轻工业局去年有19项新产品产值分别达2000万元以上，今年又形成了“凤凰”、“永久”、“飞达”牌多速自行车，“施乐”1027复印机，“白丽”多脂美容皂，“莱蒙”汽水等12种“拳头”产品，年产值都将达到5000万元。上海二轻局今年形成16种“拳头”产品，家用空调、燃气热水器、出口新颖不锈钢餐具等，产值分别将达到1000万元。"},{"type":"paragraph","text":"据市经委负责人介绍，这次博览会将邀请一万多名各地客户前来订购“四新”消费品。"}]}