{"id":778400,"date":[{"year":1988,"month":9,"day":17}],"page":"4","source":"","region":"","masthead":"奥运会特刊·周末","special_issue":"周末","column":"","genre":"","count":"502","ytitle":"","mtitle":"“老有所乐”有奖　智力大赛揭晓","ftitle":"","authors":[],"text":[{"type":"paragraph","text":"由上海市老年生活服务总社与本报《周末》版联合举办的“‘老有所乐’有奖智力大赛”日前圆满结束，共有218名读者获奖。一等奖:惠仁(65岁)、张庆年；二等奖:王佩芸(62岁)、伯序(72岁)、刘丽敏(55岁)、王静霜(69岁)、高建峰、陈洪泉；三等奖:郭鹏(75岁)、经纬斌(64岁)、李忠蘅(72岁)、徐秀宝(58岁)、任宗耀、蔡鸣、戴忠德、谢春伟、兰成扣、沈聚；纪念奖名单略。本次赛题由陶宽汝、肖武同志提供，特此鸣谢。大赛答案如下:"},{"type":"paragraph","text":"(一)画谜:翁双杰、笑嘻嘻。(二)灯谜:1、希望、人生、如意2、多年生3、白头发4、光荣退休5、好事体6、女子第一7、生长期8、优质品9、望尘莫及10、不要蛮干11、辛延年12、老上级13、公诸同好14、长期无息15、杰16、时间老人17、老有所乐18、老观众。(三)他们的爱好:张师傅爱好集邮、收藏，陈师傅爱好钓鱼、养鸟，孙师傅爱好猜谜、种花。"},{"type":"paragraph","text":"(四)从哪个字数起:周。(五)印章谜:石延年。(六)书法谜:杰作、古文。"},{"type":"paragraph","text":"周末有奖征答(22)谜底:1、渔2、分开怎能活下去3、结存4、集中收藏5、总管6、合理7、总而言之8、集合论."}]}