{"id":1143126,"date":[{"year":1998,"month":4,"day":20}],"page":"5","source":"","region":"","masthead":"国内新闻","special_issue":"","column":"","genre":"","count":"86","ytitle":"","mtitle":"国家海洋局南海环境监测中心派人到桂山","ftitle":"","authors":[],"text":[{"type":"paragraph","text":"<IMG alt=请插入12号盘，按F5键刷新后显示本插图！ src=\"D:\\inset\\1998\\04\\984k050701.JPG\">"},{"type":"paragraph","text":"<FONT class=imgaut>明磊,吴平,袁旭光</FONT>"},{"type":"paragraph","text":"<FONT class=imgsm>国家海洋局南海环境监测中心派人到桂山、伶仃等岛采集水样、分析灾情以研究对策。袁旭光　吴平　明磊摄</FONT>"}]}