{"id":1072574,"date":[{"year":1997,"month":1,"day":2}],"page":"1","source":"本报","region":"","masthead":"","special_issue":"","column":"","genre":"","count":"298","ytitle":"","mtitle":"申城雾去寒来","ftitle":"今最低温度将降至0℃左右","authors":["沈传信"],"text":[{"type":"paragraph","text":"本报讯　(记者沈传信)因前天黄海低气压发展而来的冷空气，一扫本市持续多日的迷雾天气，昨市区阵风达7级，沿海地区8至9级，使人颇感冬天的寒意。"},{"type":"paragraph","text":"据上海中心气象台副台长黄家鑫介绍，昨天晚上8时本市气温已从前天晚上8时的11.9℃骤然降至3.9℃，今天最低温度将达0℃左右。一月份历来是上海最冷的月份，从8年的气象记录来看，平均在3.3摄氏度。本市历史最低气温大多出现在一月份。目前的冷空气已使东亚上空大气环流得以改变，从元旦起本市将进入冷空气明显增多时期，气温也将明显下降，困扰本市多日的大雾天气已告结束，至少本周内不太可能有迷雾天气，而防寒保暖工作应予以加强。"}]}