{"id":289017,"date":[{"year":1953,"month":7,"day":13}],"page":"3","source":"新华社","region":"","masthead":"","special_issue":"","column":"","genre":"","count":"1186","ytitle":"","mtitle":"去年分配到鞍钢的毕业生们已成为建设鞍钢的重要力量","ftitle":"他们已初步掌握了技术并熟悉了业务","authors":[],"text":[{"type":"paragraph","text":"【新华社鞍山十二日电】　去年秋季分配到鞍山钢铁公司的一千二百余名高等学校和中等技术学校的毕业生，已成为建设鞍钢的重要力量。他们在苏联专家直接帮助和指导下，初步掌握了技术，熟悉了业务，在勘察、设计、施工管理等各项工作中，起了很大作用。"},{"type":"paragraph","text":"在鞍钢地质处地质室的十多名毕业生，已成为矿山地质勘察的骨干。他们对于工作热情、负责。许多学生在工作中提出了改进工作的关键性问题。北京大学毕业的郑宝鼎，发现绘制的地质图有不准确的地方，建议查对地质图。这项建议已被行政方面采纳，现在地质处正在开展查对图纸的工作。王集磊提出了岩心放置不能颠倒的建议，使地质情况判断的准确性提高了。在设计工作方面，新来的高等学校和中等技术学校的毕业生，就占鞍钢黑色冶金设计公司全体人员近半数，对完成鞍山钢铁工业发展远景的设计任务，贡献了很大力量。很多学生都担负着相当重要的工作，如第七炼铁炉的砌砖工程、卷扬机工程和冷却水工程的设计任务，都是由这些青年毕业生完成的。东北工学院毕业生沈介平，在某高炉的冷却水工程的设计中，到现场调查，给高炉确定了适当的冷却水用量，这样使高炉寿命得以延长。在施工方面，参加机械安装、土木建筑等工程公司的二百余名毕业生，都热情充沛地建设着大型轧钢厂、薄板轧制厂、七号高炉等巨大的工程。大型轧钢厂工地第二工段技术员洪高山，在分配工作后，就投入几个巨大设备基础工程的施工，曾经连续二十多昼夜坚持工作。为了做好轧钢机基础的排水沟工程，洪高山在寒冷的天气里钻进沟内，清除了沟里的铁丝、泥块、冰块等物，保证了工程质量。"},{"type":"paragraph","text":"参加鞍钢建设的高等学校和中等技术学校的毕业生们，虚心地学习苏联先进经验，向年老的技术人员学习，紧密地和工人合作，因而克服了工作中的困难，提高了技术水平。设计处炼铁科很多设计人员都是去年才离开学校的学生。他们首先学习了苏联为鞍钢所制的总体初步设计和苏联标准化高炉设计等资料。他们不但学习了设计方法，而且对于吸取苏联先进的设计思想，对设计我国自动化高炉有很大指导和参考意义。去年从东北工学院毕业的李国恩，由于在学习中得到启示，创造了高炉炉体砌砖工程“阶梯设计法”，给国家节省了很多耐火砖。北京大学、厦门大学等校来的几个毕业生在调查矿藏工作中为了做出正确的地质调查结论，都认真地学习了钻探技术。炼钢工程公司木模钢筋队的技术员傅忠明、马鸣骏等四人，为了提高工人的看图能力，他们和工人一起总结了工人学习图纸的经验，编出速成看图法，很多工人学会了看图。东北工学院毕业生黄立夫在见习过程中，全面地了解了鞍钢概括的生产过程、动力供应、矿区分布、矿石性质、开采和选矿的方法等情况，写出了比较全面的报告。鞍钢基本建设技术监督处检查站的技术员戴经世的见习报告，就是他在工作中学习苏联专家、工人安装和检查机械的具体经验的总结。"}]}