{"id":918343,"date":[{"year":1993,"month":9,"day":3}],"page":"2","source":"新华社","region":"北京","masthead":"综合新闻","special_issue":"","column":"","genre":"","count":"421","ytitle":"海协与海基会工作性商谈","mtitle":"圆满达到预期目的","ftitle":"","authors":["孙承斌","陈建山"],"text":[{"type":"paragraph","text":"据新华社北京9月2日电　(记者　孙承斌　陈建山)海峡两岸关系协会常务副会长唐树备今天说，刚刚结束的海协与台湾海基会工作性商谈圆满达到了预期目的，商谈的如期举行表现了两会认真执行“汪辜会谈”协议的精神。"},{"type":"paragraph","text":"唐树备是在今天下午会见台湾海基会副秘书长许惠佑一行后接受记者采访时作这番表示的。"},{"type":"paragraph","text":"8月30日至9月1日，海协副秘书长孙亚夫与海基会副秘书长许惠佑等举行了“汪辜会谈”后两会的第一次工作性商谈。在两天半的时间里，双方就全面落实“汪辜会谈”有关协议、今年内要进行的五项商谈具体安排、如何及早进行协议规定进行的经济、科技议题的商谈等问题广泛交换了意见。"},{"type":"paragraph","text":"唐树备透露，海协已向海基会建议9月下旬在北京或外地，就“违反有关规定进入对方地区人员遣返及相关问题”、“两岸有关法院之间的联系与协助”(或两岸海上渔事纠纷处理问题)、“台商在大陆投资权益及相关问题”举行进一步商谈，海协预期下一次的商谈能取得成功。"}]}