{"id":1120110,"date":[{"year":1997,"month":11,"day":28}],"page":"12","source":"本报","region":"广州","masthead":"国内新闻","special_issue":"","column":"","genre":"","count":"305","ytitle":"踏着节拍去做操　哼着名曲把家归","mtitle":"羊城一小学音乐教育有特色","ftitle":"","authors":["龚丹枫"],"text":[{"type":"paragraph","text":"本报广州专讯　广州宝源中约小学是一所没有铃声的学校。每天，该校的师生们听着约翰·施特劳斯的《拉德斯基进行曲》走进教室，当阿图尔·奥尔那柔和舒缓的《在钟表店里》的乐曲响起的时候，师生们就会发出会心的微笑——下课时间到了。在这所小学里，学生们踏着《运动员进行曲》去做早操，开播红领巾广播站的提示曲是《中国少年先锋队队歌》；云南彝族舞曲《快乐的罗嗦》代替了放学吵耳的铃声。该校由于音乐特色教育不断深化，使得每一位小学生都能在电子琴上弹奏出一首心爱的乐曲，每个班级都有歌声。该校已培养出一批小演员，单获得广东省各种乐器考级证书的就有250人次。"},{"type":"paragraph","text":"(龚丹枫)"}]}