{"id":767995,"date":[{"year":1988,"month":3,"day":26}],"page":"2","source":"","region":"","masthead":"","special_issue":"市场信息","column":"市场漫步","genre":"","count":"424","ytitle":"","mtitle":"低糖糕点将繁荣市场","ftitle":"","authors":[],"text":[{"type":"paragraph","text":"目前糕点、糖果行业有相当一部分品种的用糖量偏高。以上海市为例，糕点品种中60%的产品，用糖量高达糕点总用糖量80%。从全国来看，蛋糕、桃酥、月饼、片糕、饼干、干点心六种糕点产量大，含糖高。这种含糖高的产品结构已不适合消费者的需要。因此在保证产品质量的前提下，调整糕点产品结构，减少用糖较多品种的用糖量，发展低糖糕点，既符合消费者的要求，也是充分利用糖源的一项重要措施。"},{"type":"paragraph","text":"今年3月，全国糖制品技术协作组的糕点专业组专门研究和讨论糕点低糖化的生产和技术问题。在发展低糖糕点工作中，各地工厂企业和有关单位共同开发了一些新的甜味料，如低聚糖、高果糖浆、果葡糖浆、甜叶菊等。这些甜味料可以改善制品组织，有益人体健康。采用新的风味辅料，开发新的风味糕点如葱香、椰香、鲜味等也有利于糕点的低糖化。上海和北京在桃酥生产中采用了低聚糖后，减少了30一40%的用糖量。最近还在开发无食糖糖果。可以预料，今年下半年，丰富多彩的低糖糕点将繁荣市场。"}]}