{"id":1023781,"date":[{"year":1996,"month":1,"day":23}],"page":"7","source":"本报","region":"","masthead":"文化新闻·教卫新闻","special_issue":"","column":"","genre":"","count":"304","ytitle":"新黄浦实验学校“民办”有特色","mtitle":"实施董事会任免校长制度","ftitle":"","authors":["浦建平"],"text":[{"type":"paragraph","text":"本报讯　(记者浦建平)　在公立中学纷纷瞄准示范学校目标时，上海新黄浦集团决意要将新黄浦实验学校办成一流的示范性民办学校，昨天宣布了突出“民办”两字的一系列企业办校、专家治校的办校新措施。"},{"type":"paragraph","text":"该校在文汇报等刊出“一流学校寻找一流园丁”的招聘广告后，有400多名各地教师前往应聘，其中有哈佛大学博士。经教育和管理的专家组考评后，遴选出推荐名单给集团董事会决定。“上海市十佳青年校长”王洪伟被聘为校长。学校实行集团董事会监督下的校长负责制，董事会任免校长，校长任免副校长及教职工。该校将采取小班教学，适当阶段引进双语教学，并探索九年一贯的教育模式。"}]}