{"id":887003,"date":[{"year":1992,"month":10,"day":30}],"page":"4","source":"新华社","region":"索非亚","masthead":"国际新闻·体育新闻","special_issue":"","column":"","genre":"","count":"260","ytitle":"遭多数议员的反对","mtitle":"保政府宣布辞职","ftitle":"","authors":[],"text":[{"type":"paragraph","text":"据新华社索非亚10月28日电　保加利亚政府总理菲·季米特洛夫今晚宣布政府总辞职。"},{"type":"paragraph","text":"近月来，各派政党及民众要求现政府辞职的呼声日高。在这种情况下，政府总理在10月21日强迫议会对政府进行信任投票。28日，议会表决的结果是:在参加投票的231名议员中，111票支持并信任政府，120票反对并不信任政府。"},{"type":"paragraph","text":"议员在议会发言中认为，政府辞职是“其错误政策带来的必然的合乎逻辑的结果”。现政府是民主力量联盟的一派政府，其议员本来在议会中占多数。今天的议会表决表明，政府已遭到多数议员的反对。"}]}