{"id":207138,"date":[{"year":1950,"month":12,"day":10}],"page":"4","source":"本报","region":"","masthead":"","special_issue":"","column":"","genre":"","count":"743","ytitle":"","mtitle":"参加军校热潮不断高涨","ftitle":"育才学校五分之四同学参加　航院全体女同学昨日报了名","authors":[],"text":[{"type":"paragraph","text":"【本报讯】　各校同学响应祖国召唤的爱国行动，通过了一二一纪念会和昨天十万人的一二九示威大游行，更坚定了效忠祖国的决心，使这一支建设国防的队伍更有力更壮大了。有着光荣革命传统的育才学校，在长期的反革命斗争中，始终是站在最前线，今天美帝国主义对中国侵略的行动，更激愤了每一位育才同学。在“抗美援朝、保家卫国”的援朝志愿参军书上就有四十几位同学签上了自己光荣的名字，随时等待着祖国的号召。当参加各种军事干校的消息传到育才后，热烈迫切的火焰更燃烧在每一位等待参加同学的心中。前天在该校大礼堂上，青年团员们积极的起了带头作用，百分之七十以上的团员都光荣的报了名。少年队员们敲着锣鼓来向大姐大哥们致敬，在短短一小时中报名参加的人数已达九十二人，占全校总人数百分之八十。够条件的同学没有一个落在后面。三下沈冠一同学的父亲在抗美援朝志愿参军书上，他比儿子首先签名。这次他又亲切地鼓励儿子要他“参加军校后好好学习，建设国防。”航务学院报名参加海军干校同学已达六十四人，全校一共七位女同学于昨天庆祝一二九晚会上全部光荣地报了名。该校教授陈嘉源看到同学沸腾的爱国热情，激动地说出心底的话:“虽然我年老体弱，但当祖国需要我的时候，我愿与你们站在一起，永远作你们的战友。新沪中学的同学也都热烈地响应了祖国的号召，目前止已有六十二位同学报名。陆行中学也有五十多位同学坚决准备报名。该校教师孙惠除了自己热烈捐献支援外，并鼓励他二个正在该校高一念书的儿子参加军干校，并决定将来以每月捐献二枚手榴弹支援他们勇敢杀敌。其他有中华职校七十多同学，真如中学五十二人，光华附中二十多人，仪韵女中、启秀女中、正风中学等同学也都纷纷准备投入爱国的热潮。(各校通讯组)"}]}