{"id":36149,"date":[{"year":1938,"month":10,"day":7}],"page":"4","source":"哈瓦斯社","region":"日内瓦","masthead":"","special_issue":"","column":"","genre":"","count":"412","ytitle":"","mtitle":"捷克已提出抗议","ftitle":"指摘德国违反四强公约　各国应维护捷合法利益","authors":[],"text":[{"type":"paragraph","text":"【哈瓦斯社日内瓦六日电】关于苏台德区域割归德国事、国际委员会自指定各地方凡日耳曼族居民至少占有人口总数百分之五十一者、均应由德国军队在本月七日至十日之间、予以占领之后、捷克国驻国联会代表团办事处、顷发表公报提出抗议云、“按之初步情报、国际委员会顷所决定之事、对于捷克国之经济利益与内国交通妨害实甚、国际委员会捷克国各专家、已于昨日自柏林返国报告、捷克国政府即干昨日晚间举行会议、加以讨论、并决定训令各该专家、在本日遄返柏林、而以全力维护捷克民族之合法利益、查国际委员会昨日开会时、德国代表团曾提出新要求、意欲兼并范围甚广之土地、并最富庶各城市各工业区、既重要交通线在内、抑知各该城市与工业区、在种族观点上、实以捷克族人占大多数、自非捷克国所能割让、德国政府一方面既为苏台德区域日耳曼人要求民族自决权利、一方面乃竟不许捷克族人享受同样权利、此其所为、实属违反慕尼黑协定”云"}]}