{"id":909285,"date":[{"year":1993,"month":6,"day":3}],"page":"5","source":"本报","region":"","masthead":"长江新潮","special_issue":"长江新潮","column":"","genre":"","count":"206","ytitle":"","mtitle":"《中国三峡工程报》创刊","ftitle":"","authors":["耿长森"],"text":[{"type":"paragraph","text":"本报讯　本报经国家新闻出版总署批准，由中国长江三峡工程开发总公司主办的《中国三峡工程报》5月在湖北省宜昌市创刊并向全国发行。李鹏总理为该报题写了报头。"},{"type":"paragraph","text":"该报将系统介绍三峡工程的规模、效益、勘测、设计、施工、管理及移民情况，全面反映社会各界对三峡工程的意见、建议和要求，及时报道工程建设动态和成就。另外还开辟了《全国水电》、《世界水电》栏目来登载国内外重大水电信息和动态。"},{"type":"paragraph","text":"(耿长森)"}]}