{"id":742848,"date":[{"year":1987,"month":2,"day":21}],"page":"1","source":"新华社","region":"","masthead":"","special_issue":"","column":"","genre":"","count":"201","ytitle":"","mtitle":"美国取消对波兰经济制裁","ftitle":"","authors":[],"text":[{"type":"paragraph","text":"据新华社华盛顿19日电　美国19日宣布取消对波兰实行的经济制裁。"},{"type":"paragraph","text":"美国的这一决定，是里根总统在白宫会见美籍波兰人领袖后，发表的一项声明中宣布的。美国是因波兰政府于1981年底宣布在国内实行军事管制而决定对波兰实行经济制裁的。"},{"type":"paragraph","text":"里根在声明中表示，美国决定取消对波兰的经济制裁，恢复给予波兰的贸易最惠国待遇，取消美国官方向波兰提供货款的禁令。他说，这一决定是朝着美波关系正常化迈出的第一步。"}]}