{"id":871951,"date":[{"year":1992,"month":6,"day":12}],"page":"3","source":"本报","region":"锦州","masthead":"科教文卫新闻","special_issue":"","column":"","genre":"","count":"460","ytitle":"","mtitle":"黄启民首创人体经纬定位法","ftitle":"世界针灸联合会向各国推荐这一成果","authors":["刘子阳"],"text":[{"type":"paragraph","text":"本报锦州专讯　(《辽宁日报》记者刘子阳)在人体上设立经纬坐标纵横数据，然后在人体体表上确定任何一个点、一条线或一个区域，都能达到准确地定位。锦州市凌河区医院针灸大夫黄启民发明的“人体经纬定位法”，世界针灸联合会向各国推荐这一成果。他编著的《人体经纬定位法》一书，6月上旬已由辽宁科学技术出版社出版发行。"},{"type":"paragraph","text":"今年65岁的黄启民30年前开始研究针灸疗法，感到过去传下来的取穴法，无论是“骨度法”还是“同身寸法”，都不能准确定位。理论上人体的300多个常用穴位，临床只能用百十个左右，大部分是有穴难定、有穴难取。他从地球仪上得到启发，大胆效法地球仪上的经纬定位法，开始了在人体上用经纬线定位的研究。他先后求助300人，对每人进行120项测量，共取得3.6万个数据。在全国许多著名专家帮助和有关部门支持下，他用30年心血撰写的37万多字、多幅插图的《人体经纬定位法》终于问世。黄启民的定位方法在临床各科以及法医学和人体解剖学、物理诊断和物理治疗等都有实用价值。"}]}