{"id":369717,"date":[{"year":1958,"month":5,"day":31}],"page":"1","source":"本报","region":"杭州","masthead":"","special_issue":"","column":"破除迷信　敢想敢为　向技术革命文化革命大进军","genre":"","count":"272","ytitle":"","mtitle":"杭州宣传总路线","ftitle":"形式多样　气氛热烈","authors":[],"text":[{"type":"paragraph","text":"【本报杭州30日专电】　今日杭州全市在过欢乐的节日。成千上万的工人、学生、文艺工作者、机关干部等，在总路线鼓舞下，组成了一支庞大的宣传队伍。他们热情充沛地轮流在大街小巷、茶馆酒楼进行宣传。到处都是喧腾的锣鼓声和歌唱声。这些热情的宣传员连夜编成各色各样的说唱、舞蹈，结合总路线内容化装表演，受到了群众热烈欢迎。入夜，全市五色缤纷的霓虹灯，一齐开放。白堤旁树立着巨大的“坚决、彻底实现总路线”的红色霓虹灯，倒映在西子湖里，分外美丽。庞大的宣传队伍非常活跃，使总路线的宣传深入人心。"}]}