{"id":901602,"date":[{"year":1993,"month":3,"day":17}],"page":"3","source":"本报","region":"","masthead":"综合新闻","special_issue":"","column":"","genre":"","count":"316","ytitle":"","mtitle":"一声范老师　热泪沾衣襟","ftitle":"上海音乐界人士昨向范大雷遗体告别","authors":["周玉明","邓瞳瞳"],"text":[{"type":"paragraph","text":"本报讯　(记者周玉明　邓瞳瞳)昨天，龙华殡仪馆大厅里久久地萦绕着悠长而忧郁的旋律——拉赫玛尼诺夫的第二钢琴协奏曲取代了那着重复了多少次的哀乐。前来向上音附中范大雷教授遗体告别的人们悲痛而11又肃静。大幅挽联上，“英年早逝”、“大器晚成”的字眼灼人眼睛。桑桐、朱践耳、吴乐懿等两鬓花白者在这位黑发人的遗体前欲言无语。就在数日前，九十高龄的贺绿汀老人在写给孔样东、周挺钢琴演奏会的信用还曾为刚过四十七岁生日的范大雷祝福。"},{"type":"paragraph","text":"校友、同事，学生、朋友们，静静地目睹着钢琴事业的一大遗憾。上音副院长王建中在悼词中引用了上音附小学生的话:“音乐家伟大，可范老师创造了音乐家……”"}]}