{"id":556951,"date":[{"year":1976,"month":12,"day":20}],"page":"3","source":"新华社","region":"北京","masthead":"","special_issue":"","column":"","genre":"","count":"369","ytitle":"","mtitle":"王震副总理会见朝鲜科学院代表团","ftitle":"中朝两国科学院一九七七至一九七八年科学合作计划在京签订","authors":[],"text":[{"type":"paragraph","text":"新华社北京一九七六年十二月十九日电　国务院副总理王震今天下午会见以朝鲜科学院副院长洪群标为团长的朝鲜科学院代表团，同他们进行了十分亲切友好的谈话。朝鲜驻中国大使玄峻极参加了会见。中国科学院副院长吴有训，有关方面负责人郁文、何章明、张岐、王守武、黄坤益等参加了会见。"},{"type":"paragraph","text":"新华社北京一九七六年十二月十九日电　中国科学院和朝鲜民主主义人民共和国科学院一九七七至一九七八年科学合作计划今天在北京签订。中国科学院副院长吴有训、朝鲜科学院副院长洪群标分别代表中朝两国科学院在合作计划上签字。"},{"type":"paragraph","text":"朝鲜驻中国大使玄峻极参加了签字仪式。"},{"type":"paragraph","text":"我有关方面负责人郁文、何章明、张岐、王守武、黄坤益等也参加了签字仪式。"},{"type":"paragraph","text":"为祝贺中朝两国科学院科学合作计划的签订，吴有训副院长当天晚上设宴招待朝鲜同志。"}]}