{"id":346403,"date":[{"year":1957,"month":4,"day":29}],"page":"4","source":"","region":"","masthead":"","special_issue":"新闻窗","column":"新闻周历","genre":"","count":"602","ytitle":"","mtitle":"新闻周历","ftitle":"","authors":[],"text":[{"type":"paragraph","text":"(4月21日—27日)"},{"type":"paragraph","text":"4月21日"},{"type":"paragraph","text":"毛主席接见日本社会党访华团。"},{"type":"paragraph","text":"新华社报道:苏联就中近东问题，再次照会美英法，要求谴责武力手段。"},{"type":"paragraph","text":"日本拟出修改日美条约的草案，不让美军驻在日本本土。"},{"type":"paragraph","text":"4月22日"},{"type":"paragraph","text":"北京35万人讨论毛主席报告，彭真就所提问题作了解答。"},{"type":"paragraph","text":"张奚若和浅沼稻次郎发表共同声明，一致认为中日恢复国交时机已届。"},{"type":"paragraph","text":"英共全国特别代表大会闭幕，决定争取早日大选。"},{"type":"paragraph","text":"杜勒斯吹嘘要扩大侵略集团和颠复人民民主国家。"},{"type":"paragraph","text":"4月23日"},{"type":"paragraph","text":"上海25万群众集会，欢迎伏罗希洛夫主席。"},{"type":"paragraph","text":"苏联决定公布苏英法三国首脑来往信件，使公众了解各大国对中近东真正态度。"},{"type":"paragraph","text":"美英法蛮横侵害埃及主权，竟要求安理会讨论运河问题。"},{"type":"paragraph","text":"约里奥—居里大声疾呼，立即停止核武器试验。"},{"type":"paragraph","text":"4月24日"},{"type":"paragraph","text":"高等教育部和教育部发表今年全国高等学校招考新生规定。"},{"type":"paragraph","text":"约旦局势发生剧变，哈利迪内阁辞职，哈希姆组成亲西方政府；全国宣布戒严令，所有政党被解散。"},{"type":"paragraph","text":"埃及重申君士坦丁堡公约，保证运河自由通航。"},{"type":"paragraph","text":"4月25日"},{"type":"paragraph","text":"毛主席接见柬埔寨经济代表团团长。"},{"type":"paragraph","text":"伏罗希洛夫主席抵杭州。"},{"type":"paragraph","text":"美国第六舰队开往中东。企图恫吓约旦人民。"},{"type":"paragraph","text":"苏联领导人警告杜勒斯不要冒险，“解放”政策决无成功希望。"},{"type":"paragraph","text":"4月26日"},{"type":"paragraph","text":"中共上海市委第一书记柯庆施号召中小学教师大胆提意见。"},{"type":"paragraph","text":"文化系统初步发现八项内部矛盾。"},{"type":"paragraph","text":"4月27日"},{"type":"paragraph","text":"上海文艺界对创作问题和出版工作提出批评。"},{"type":"paragraph","text":"我和大常委会通过决议支持反氢弹斗争。"},{"type":"paragraph","text":"浅沼返抵东京，发表声明，准备发动争取恢复中日邦交的群众运动。"}]}