{"id":1165305,"date":[{"year":1998,"month":8,"day":29}],"page":"11","source":"","region":"","masthead":"文汇特刊","special_issue":"海外广角","column":"教育园地","genre":"","count":"455","ytitle":"","mtitle":"从英特网上获取牛津学位","ftitle":"","authors":["叶尔"],"text":[{"type":"paragraph","text":"不久，全球各地的学生可望不出国门，不需要进入任何一所大学，而可从英特网上获得自己朝思暮想的英国牛津大学的学位证书。"},{"type":"paragraph","text":"据英特版的《伦敦时报》称，首次通过联机学习获得的牛津大学的学位是医学计算机与软件工程的硕士学位，以后将逐渐扩大到大学学士学位。"},{"type":"paragraph","text":"牛津大学准备招收网上学生的目的之一是，让全球更多的学子可望成为梦寐以求的著名的牛津大学的学生，并使牛津大学的国际声誉扩大到远距离学习方面。"},{"type":"paragraph","text":"牛津大学的网上学生可使用e-mail在网上展开讨论，参加网上座谈会等一系列活，动，网上教学的全部课程由牛津大学负责监管。各国网上学生通过非全日制四年以上的学习，可取得牛津大学硕士学位。当然，牛津大学偶尔还会同学生进行面对面的单独教授。尽管学生的学习形式是在网上进行的，但考试仍将集中在牛津大学进行。"},{"type":"paragraph","text":"牛津大学招收网上学生的行动将得到微型软件公司的合作创建者保罗·艾伦的支持。但是，此举可能会受到传统保守主义者的反对，他们认为，成为牛津大学的毕业生必须亲身体验一下在牛津大学校园学习的滋味。"},{"type":"paragraph","text":"叶尔"}]}