{"id":653307,"date":[{"year":1983,"month":5,"day":19}],"page":"1","source":"新华社","region":"太原","masthead":"","special_issue":"","column":"","genre":"","count":"306","ytitle":"","mtitle":"农校讲师李志超著书近百万字","ftitle":"","authors":[],"text":[{"type":"paragraph","text":"据新华社太原五月十八日电　山西省原平农校讲师李志超业余从事科普创作，十年发表六百三十多篇科普文章，编著了十本农业科技书籍，近一百万字。五月上旬，山西省人民政府表彰了他为普及农村科学技术做出的贡献。"},{"type":"paragraph","text":"在和农民的广泛接触中，李志超发现，农民经常遇到各种科学技术问题，需要解答。他随时注意记录这些问题，然后翻阅有关资料，编写通俗易懂的科普文章。"},{"type":"paragraph","text":"李志超交了许多农民朋友，还建立了不少科学研究活动点，随时了解农民对科学技术的需求。他虚心向土生土长的农民科学家求教，帮助农民科学家总结推广实践经验。十年来，李志超先后总结了五个县的七位农民科学家的经验，其中有玉米育种、发酵饲料，还有酸菜汤诱杀金龟子等。"}]}