{"id":1221266,"date":[{"year":1999,"month":10,"day":15}],"page":"3","source":"","region":"","masthead":"文化新闻","special_issue":"","column":"旅游演出今秋上海全面出击,焦点透视","genre":"","count":"337","ytitle":"","mtitle":"实景演出别具特色","ftitle":"","authors":["金涛"],"text":[{"type":"paragraph","text":"目前，上海旅游市场的飞速发展，使各剧团开发旅游剧目的意识空前增强。"},{"type":"paragraph","text":"在剧目营销上，艺术节参演剧目京剧《宝莲灯》别具一格。近日，京剧院正在广泛联络驻沪外国人，五位主演和留学生开展联谊活动，请外国朋友参观京剧院，安排京剧小品演出。他们盯住外国游客，按“旅游剧目”样式进行包装策划。据了解，上海曾有过类似的旅游剧目一如京剧《盘丝洞》，但多是为剧团赴海外演出排演，缺乏具有本地特色的演出。目前，上海剧团策划中的一些新剧目，文化产业运作趋势更加明显，如昆剧团和南市区旅游部门合作，打算定点“三山会馆”演出昆曲《琵琶行》，专门定位海内外游客。青浦大观园有意和上海越剧院合作，开发“红楼风情旅游线”，尝试搞实景演出。"},{"type":"paragraph","text":"本报记者金涛"}]}