{"id":1152629,"date":[{"year":1998,"month":6,"day":14}],"page":"7","source":"","region":"","masthead":"都市新潮·广告","special_issue":"都市新潮","column":"家电师傅","genre":"","count":"712","ytitle":"","mtitle":"从暖水瓶到家庭热水中心","ftitle":"","authors":[],"text":[{"type":"paragraph","text":"现代科技的发展，使人们的日常生活方式亦随之发生着不断的变化。就说家庭中的热水供应吧。早些年，人们要先用煤炉烧开，然后灌进暖水瓶里保温，很不方便。前些年出现了电热水器和燃气热水器，一时使家庭喝热水或洗澡顿感方便了许多。今天，不管是冬季还是夏季，人们在生活中对热水的要求越来越多，家庭的热水供应事实上已经超越人们对一件普通家用电器的要求。"},{"type":"paragraph","text":"国外流行的一句话是，高质量的家居生活需要两个最基本的标志，一是任何一个角落都能够享受四季如春的空调设备，二是任何一个水龙头打开来都有热水供应。于是，市场上不断有热水器新品推出。日前，青岛一家著名家电企业倡导的一个“家庭热水中心”的新概念正引起注意，这或许可作为现在家庭热水供应特征的一种概括吧。家庭热水供应中心给人们带来了哪些新的生活革命呢?"},{"type":"paragraph","text":"热水供应的范围扩大。这种大容量的电热水器就像一个锅炉。热水可以通过管道接到任何需要用热水的地方。洗菜、洗手、洗衣，如果配上铝制的暖气片，还可以接到暖气上循环使用。"},{"type":"paragraph","text":"热水供应保证全天候。由于保温层采用了超厚聚胺酯发泡材料，可以24小时保温。因而，尽管热水器一天工作的时间只有十几分钟，但可以保证你随时用到需要的热水。"},{"type":"paragraph","text":"与过去的简单热水器比较，热水中心出来的水的水质也不一样了。为了除垢，热水器内部设有吸附装置，可以清除水中的重金属离子，软化水质，从而有效地养护肌肤。"},{"type":"paragraph","text":"热水中心全部采用进口电子原件，电热管使用进口的陶瓷加热管，并实现了水电安全隔离，又加装了日本进口的漏电保护器，从而保证了百分之百的安全性。"},{"type":"paragraph","text":"家庭热水供应从暖瓶时代走进热水中心时代，充足方便的热水供应，使现代人的家居生活质量又有了一个根本性的改善。"}]}