{"id":997948,"date":[{"year":1995,"month":7,"day":22}],"page":"2","source":"本报","region":"北京","masthead":"综合新闻·每日行情","special_issue":"","column":"","genre":"","count":"311","ytitle":"","mtitle":"彪马街头足球赛在京抽签","ftitle":"华东技工学校篮球赛在沪开幕","authors":["王胜","叶志明"],"text":[{"type":"paragraph","text":"本报北京七月二十一日专电　(记者叶志明)我国首次举办的九五彪马街头足球锦标赛今天举行抽签仪式。"},{"type":"paragraph","text":"根据抽签，火车头、辽宁、大连、八一和佛山五支球队分在甲组，上海、四川、天津、北京和沈阳五队分在乙组。"},{"type":"paragraph","text":"这次彪马街头足球锦标赛将于七月二十三日在北京劳动人民文化宫举行。两个组通过单循环赛选出两队出线，再由交叉淘汰赛决出冠军队。"},{"type":"paragraph","text":"本报讯　来自华东地区各省市由技校学生组成的十一支男、女篮球队昨天云集本市，参加了在上海石化工业学校举行的首届技工学校篮球联赛华东赛区开幕式。比赛将于今天起到二十六日结束，获得男、女前二名的球队将于八月下旬赴哈尔滨参加总决赛。"},{"type":"paragraph","text":"(王胜)"}]}