{"id":89760,"date":[{"year":1946,"month":4,"day":2}],"page":"4","source":"","region":"","masthead":"","special_issue":"读者的话","column":"","genre":"","count":"258","ytitle":"","mtitle":"街头人语","ftitle":"","authors":[],"text":[{"type":"paragraph","text":"街头人"},{"type":"paragraph","text":"昨天是愚人节，报上仍有故意说点谎话。以资点缀的，但似乎也没有多大意味。说的落寞，聪者淡然。"},{"type":"paragraph","text":"“愚人节”在外国，也许是很热闹的吧?在中国却往往只是无味的扯淡。因为我们每天几乎都在过“愚人节”，对于一切的说谎，实在引不起什么兴味了。"},{"type":"paragraph","text":"报载行政院宋院长在沪召开重要会议，讨论的是工潮问题。"},{"type":"paragraph","text":"是的，工潮太成问题了，谁都希望政府能够拿出办法来。但强硬的压制决不是好办法。"},{"type":"paragraph","text":"有谈政治掌故者，说张怀芝为山东督军时赴省议会演说云:“这议会的洋楼好像一只鸟笼，你们就是鸟，现在吃饱了，可以不叫了!”"},{"type":"paragraph","text":"好一个吃饱的鸟，闻之哑然失笑。"}]}