{"id":669567,"date":[{"year":1984,"month":2,"day":26}],"page":"1","source":"新华社","region":"北京","masthead":"","special_issue":"","column":"","genre":"","count":"346","ytitle":"李先念号召全国人民积极参加文明礼貌月活动","mtitle":"创造两个文明的优异成绩 迎接国庆三十五周年到来","ftitle":"以建设文明单位为目标，继续治理“脏、乱、差”，创“三优”新水平","authors":[],"text":[{"type":"paragraph","text":"据新华社北京二月二十五日电　国家主席李先念今天发表了迎接一九八四年全民文明礼貌月的广播电视讲话，希望大家以创造社会主义物质文明和精神文明的优异成绩，迎接国庆三十五周年。"},{"type":"paragraph","text":"他要求今年的文明礼貌月活动，要以创建文明单位为目标，继续综合治理“脏、乱、差”，使倡导优质服务、建立优良秩序、创造优美环境的活动，更加普及，更加深入，提高到新的水平。"},{"type":"paragraph","text":"李先念主席指出，开展文明礼貌月活动的过程，应该同时是结合群众的思想实际，创造群众喜闻乐见的多种形式，向群众进行集体主义、爱国主义、社会主义、共产主义思想教育的过程。"},{"type":"paragraph","text":"<IMG alt=请插入8号盘，按F5键刷新后显示本插图！ src=\"D:\\inset\\1984\\02\\842q010101.JPG\">"},{"type":"paragraph","text":"<FONT class=imgsm>李先念主席发表广播电视讲话"},{"type":"paragraph","text":"新华社记者摄(传真照片)</FONT>"}]}