{"id":921508,"date":[{"year":1993,"month":10,"day":5}],"page":"7","source":"","region":"","masthead":"法庭内外","special_issue":"法庭内外","column":"","genre":"","count":"821","ytitle":"","mtitle":"挪用公款犯罪突出 亟需引起各方重视","ftitle":"","authors":["青剑"],"text":[{"type":"paragraph","text":"青剑"},{"type":"paragraph","text":"随着市场的活跃，经济交往的增多，本市挪用公款犯罪明显增多，而且手法多变，数额较大，亟需引起各有关部门的重视。这里揭露几种常见的挪用公款手法，以利于各单位制订出一些有效的防范措施，管好自家的钱袋。"},{"type":"paragraph","text":"一、暗渡陈仓法。特征是支出款不到位或部分不到位。钱款明的汇往了甲处，但实际却在做了手脚后汇到了乙处。如厂长徐某，在私营办厂时欠下昆山市某单位1.7万元，经法院调解限期归还。徐逾期未还，对方申请执行。徐便用本厂的空白转帐支票，分二次在银行联上填写收款单位为法院，金额1.7万元，将钱汇到了法院帐上；而在支票存根联上收款单位一项上却填上了一业务单位粉末厂，用途写了购粉后交会计报帐。"},{"type":"paragraph","text":"二、瞒天过海法。特征是收入不入帐或收入部分不入帐。如厂长顾某，以本厂名义向某公司借款10万元。他只将其中5万元汇到厂内，另5万元却盖了支票背书后转到了一个体承包户帐上，借给个体户做生意。"},{"type":"paragraph","text":"这种收入不入帐的手法在供销业务人员中也较多发生。如某乡办厂有5名供销员在销售本厂产品后，将收到的钱款挪作己用。"},{"type":"paragraph","text":"三、偷梁换柱法。特征是冒名顶替，名公实私。如供销员毛某，借自己所在厂与上海一车灯有限公司的业务交往，多次以本单位的名义向对方单位购进废塑料装运回家，经分拣后出售营利。而对方则将这些帐记在了应收款往来帐上。"},{"type":"paragraph","text":"近年挪用公款案上升的原因，一方面是由于私营经济、承包经济、证券市场、期货市场等的迅速发展，资金在短期内占用后就可获取暴利，加上一些人认为挪用只要归还就没事了，因此，有人就想“借鸡生蛋”以此致富。另一方面是由于各种审计监督机制的削弱，一些规章制度形同虚设；厂长、经理钱权一手抓，支票在他口袋里，想怎么开就怎么开，盖个背书章钱可从这里飞往别处；没有行之有效的对帐制度，巨额现金的交易等等，总之钱好捞，如果主管、经管人员素质差、难免不出问题。因此，建议各单位加强审计监督工作、严格各项管理措施和财务管理制度，切实管好自家的钱袋。"}]}