{"id":413359,"date":[{"year":1960,"month":12,"day":30}],"page":"4","source":"新华社","region":"","masthead":"","special_issue":"","column":"","genre":"","count":"441","ytitle":"老挝爱国武装力量英勇战斗","mtitle":"继续在万象周围和各地打击叛军","ftitle":"","authors":[],"text":[{"type":"paragraph","text":"【新华社河内28日电】　据寮国战斗部队电台今晚广播，老挝爱国战线党万象省委员会发表声明指出，在老挝王国政府撤出万象市后，老挝王国政府军队和爱国武装力量目前正在万象市周围和全国其他各省对叛军进行战斗。"},{"type":"paragraph","text":"声明指出，在西凯、农蓬、农布、东努姆地区和通往北山、塔德和塔戎公路两旁发生的战斗中，我军击毁敌军不少坦克、装甲车和吉普车等，敌军被打得四处乱窜。同胞们都支持我们的正义斗争，在上述战斗中都同我们的军队协作。"},{"type":"paragraph","text":"声明还说，配合在万象的战斗，许多天来，其他各省军队和人民正在进军攻打琅勃拉邦市的叛军。"},{"type":"paragraph","text":"声明说，目前，我们已经占领了川藏一些地方，甘蒙省的坎格、巴桂和塔发宗等地点。目前，正向甘蒙市进军。在沙湾拿吉省，我们也已经占领了布拉发据点，并且正在伏击第九号公路上的敌人。"},{"type":"paragraph","text":"声明说，在巴色省，我们占领了菲派市，并严密地控制了通往芒空的公路。"},{"type":"paragraph","text":"声明指出，根据政府的命令撤出万象市，并不是我们败给了敌人。“尽管斗争还很困苦，但是最后胜利一定属于我们。”"}]}