{"id":960788,"date":[{"year":1994,"month":10,"day":26}],"page":"4","source":"","region":"","masthead":"国内新闻","special_issue":"","column":"伽马先生答客问","genre":"","count":"341","ytitle":"","mtitle":"解高人之忧 三鸣养生王","ftitle":"","authors":[],"text":[{"type":"paragraph","text":"自10月19日《礼拜三·三鸣健康物语》推出后，读者来信如雪片般飞来。他们苦恼甚多，急盼伽马先生解忧。"},{"type":"paragraph","text":"来信问得最多的是:为什么说γ—亚麻酸治“三高”有奇效?"},{"type":"paragraph","text":"答:高血脂血液中的甘油三脂、胆固醇增高，血脂增高会导致高血压、心脑血管病，诱发心肌梗塞、中风等，危及您的生命。高血糖则是糖尿病的重要症状。现代医学证实:这些病魔的侵入，都与人体缺乏一种叫γ—亚麻酸的物质有直接关系。"},{"type":"paragraph","text":"富含Y—亚麻酸的三鸣养生王能促进体内前列腺素的生成，在前列腺素的作用下，人体各器官系统趋相向平衡，从而达到防病与治病的目的，而且化学合成药不同的是，它没有任何副作用。所以，用生物工程法制取Y—亚麻酸是国家“七·五”、“八·五”攻关项目，1994年又被列入国家“火炬”计划。"},{"type":"paragraph","text":"<IMG alt=请插入10号盘，按F5键刷新后显示本插图！ src=\"D:\\inset\\1994\\10\\94aq041501.JPG\">"}]}