{"id":960815,"date":[{"year":1994,"month":10,"day":26}],"page":"6","source":"本报","region":"南京","masthead":"体育新闻","special_issue":"","column":"","genre":"","count":"273","ytitle":"","mtitle":"“双叶”争王","ftitle":"","authors":["林峰"],"text":[{"type":"paragraph","text":"10月25日专电南京交行杯中国首届国际象棋棋王赛今天完成决赛第一轮。叶江川后走弈和谢军，叶荣光先走战平汪自力。这样，在前4名组中，“两叶”各积1.5分领先，谢军和汪自力各积0.5分随后。"},{"type":"paragraph","text":"今日谢军和叶江川之战为全场瞩目，谢以王前兵起步，叶以西西里防御舍维宁根变倒应战。双方输攻墨守，弈来各有章法，中局几番拚搏，虽有顾忌，局面简化后，转成各有后车五兵，于52回合，女子世界冠军谢军提和，她的教练叶江川欣然应诺。"},{"type":"paragraph","text":"26日决赛第二轮也即最后一轮的对弈形势是前四名组中，叶江川对叶荣光，汪自力对谢军。首届棋王将在“两叶”之中产生。"},{"type":"paragraph","text":"()"}]}