{"id":200355,"date":[{"year":1950,"month":10,"day":19}],"page":"4","source":"","region":"","masthead":"","special_issue":"","column":"在学校里","genre":"","count":"278","ytitle":"","mtitle":"在学校里","ftitle":"","authors":["管维霖","吴南群","噩鱼"],"text":[{"type":"paragraph","text":"△沪江附中师生为纪念鲁迅先生逝世十四周年，特编辑纪念专刊墙报，图书馆也将先生所有著译及有关先生的书籍陈列，同时举行座谈会。"},{"type":"paragraph","text":"(管维霖)"},{"type":"paragraph","text":"△市师夜中学为使同学更深入地明了新爱国主义和国际主义精神，在十六日集会课上特请中苏友好协会陆星南先生讲“中苏关系”。　(吴南群)"},{"type":"paragraph","text":"△圣芳济中学师生一千多人于十二日上午集体参观“从猿到人”展览会，通过这次展览，师生们开始确信劳动创造人类、创造世界的真理。纠正了过去轻视劳动的错误观点。"},{"type":"paragraph","text":"(噩鱼)"},{"type":"paragraph","text":"△南洋中学教职员工会定今午举行成立大会，同学们准备了许多文娱节目庆贺自己教师工会的成立。　(南中通讯组)"}]}