{"id":600457,"date":[{"year":1980,"month":8,"day":28}],"page":"3","source":"新华社","region":"北京","masthead":"","special_issue":"","column":"","genre":"","count":"466","ytitle":"","mtitle":"党中央、国务院这个头带得好","ftitle":"北京饭店就处理“渤二”事件的决定进行民意测验","authors":["王显周","邱永生"],"text":[{"type":"paragraph","text":"据新华社北京八月二十七日电　新华社通讯员王显周、记者邱永生报道:北京饭店二十六日对国务院严肃处理“渤海二号”翻沉事故的决定，在职工中进行了一次民意测验，"},{"type":"paragraph","text":"二十六日下午进行的这次民意测验，共发票一百张，采用不记名方式，厨师、服务员、科室干部争相参加。测验结果是:表示拥护国务院决定的六十九人；不赞成的一人；无所谓的一人；不加评论的八人；不知道此事的四人；认为对宋振明、康世恩两位同志处理轻了的有十五人；认为处理过重的二人。"},{"type":"paragraph","text":"在民意测验过程中，很多人积极向党委宣传科的同志发表自己的看法。不少服务员说:国务院出面给一位副总理记大过处分，解除一个部长的职务，而且很快公布于众，这是建国三十一年来的第一次。有的说:这件事表明，中央的部长犯法与民同罪。党中央带头严格执法，我们国家大有希望，有的干部反映:功是功，过是过，功过分明，奖惩严明，实事求是。这体现了党的传统作风在恢复发扬。党中央、国务院这个头带得好，民心大振，对搞好党风、民风，一定会产生重大的良好影响，"}]}