{"id":529716,"date":[{"year":1973,"month":8,"day":9}],"page":"3","source":"","region":"","masthead":"","special_issue":"","column":"读者来信","genre":"","count":"476","ytitle":"","mtitle":"制冷压缩机为什么睡大觉?","ftitle":"上海制冷设备厂拒不修理本厂的产品","authors":[],"text":[{"type":"paragraph","text":"编辑同志:"},{"type":"paragraph","text":"上海工业玻璃五厂职工，从社会主义全局利益出发，把方便让给别人，把困难留给自己。他们这种发扬“龙江”风格的动人事迹，值得我们很好学习。可是，就在大搞社会主义协作的动人事迹到处涌现的大好形势下，上海制冷设备厂的某些人却无动于衷。"},{"type":"paragraph","text":"今年五月初，上级公司调拨给我厂一台由上海制冷设备厂制造的价值一万二千余元的制冷压缩机。我们在使用时，发现这台机器有故障，需要修理，但是由于这种机器内部构造比较复杂，厂里无人能修，我们只得向上海制冷设备厂求援。但该厂生产部门的某些人很不耐烦，不肯接受这项修理任务。后来，经过再三要求，他们把此事踢到修理部门，修理部门也不肯修理，推说这是业务部门的事情，最后，他们又借故拒绝了这项修理任务。现在，我们厂急需要用制冷压缩机，而这么大的一台机器由于没人修理，只好放在食堂里睡大觉，我们看了很痛心。"},{"type":"paragraph","text":"我们希望上海制冷设备厂的某些同志，认真学习先进单位的先进事迹，从思想上找差距，克服本位主义，树立为人民服务的思想，发扬兄弟厂之间的社会主义协作精神。"},{"type":"paragraph","text":"上海灯泡一厂动力组"}]}