{"id":472204,"date":[{"year":1965,"month":12,"day":14}],"page":"2","source":"","region":"","masthead":"","special_issue":"","column":"读者　作者　编者","genre":"","count":"320","ytitle":"","mtitle":"读者作者编者","ftitle":"","authors":["许勇争"],"text":[{"type":"paragraph","text":"编辑同志:"},{"type":"paragraph","text":"我很想学些唯物辩证法，但自己的水平很低，不知怎么学。自从你报办了《学点唯物辩证法》专栏以来，我很喜爱看。不少文章从实际工作出发，谈一些辩证法，对我们教师来说，读来很亲切。这些文章指导了我的工作。当发现学生们有了缺点和错误时，我不再象以前那样，老是“训”学生了，而首先想到在《为什么将3分改5分?》一文中说的:“当我们发现了学生、孩子的缺点时，首先不要责备他们，而应该冷静地回想一下我们自己平时的工作、言行怎样，言教身教怎样。”有时事情做坏了，又想到怎样变坏事为好事。"},{"type":"paragraph","text":"我也想学习和运用辩证法，来总结一下自己的工作，为这个专栏写稿。但不知道怎样写才好，你们能不能给我一些帮助?"},{"type":"paragraph","text":"吴江县盛泽镇荡口街小学"},{"type":"paragraph","text":"许勇争"}]}