{"id":1059379,"date":[{"year":1996,"month":10,"day":4}],"page":"4","source":"新华社","region":"耶路撒冷","masthead":"国际新闻","special_issue":"","column":"","genre":"","count":"242","ytitle":"数万以色列人和平集会","mtitle":"抗议政府强硬政策","ftitle":"","authors":[],"text":[{"type":"paragraph","text":"据新华社耶路撒冷十月二日电　在以色列“现在就和平”组织的号召下，数万名以色列人今天在特拉维夫举行和平集会，抗议利库德集团领导的以色列政府推行强硬政策。"},{"type":"paragraph","text":"参加集会的以色列人手持写有“现在就和平”等标语。一些以色列著名歌唱家还在集会上高唱和平圣歌。"},{"type":"paragraph","text":"以色列工党议员、前工党政府总理府部长贝林在集会上呼吁内塔尼亚胡在结束华盛顿首脑会晤后立即恢复以色列同巴勒斯坦、叙利亚和黎巴嫩的和谈。他要求内塔尼亚胡首先考虑以色列和以色列人民的利益，而不是美国的利益。"}]}