{"id":1192462,"date":[{"year":1999,"month":3,"day":13}],"page":"2","source":"本报","region":"","masthead":"综合新闻","special_issue":"","column":"","genre":"","count":"261","ytitle":"","mtitle":"执法者专家共同“坐堂” 接受消费者咨询投诉","ftitle":"本报与市技监局今明联合举办“建材装潢消费讲座”等活动","authors":[],"text":[{"type":"paragraph","text":"本报讯　为迎接“3·15”国际消费者权益日，文汇报和市技术监督局今天和明天上午在常德路1436号德诚大厦(近宜昌路，公交车24路、138路终点站)举办“建材装潢消费讲座与咨询、投诉活动”。"},{"type":"paragraph","text":"此项活动由中国质量万里行上海投诉站和文汇报群众工作部承办，由市建筑装潢协会家庭装饰委员会、上海申瑞建材装潢公司协办。"},{"type":"paragraph","text":"活动内容:邀请执法部门人员与专家，就建材与装潢这一专题，设摊接受消费者咨询、投诉，并于今天上午举行“建材装潢消费讲座”。"}]}