{"id":611616,"date":[{"year":1981,"month":4,"day":10}],"page":"1","source":"本报","region":"","masthead":"","special_issue":"","column":"","genre":"","count":"175","ytitle":"","mtitle":"市七届人大三次会议主席团首次会议","ftitle":"推选陈国栋、胡立教等十一人为常务主席","authors":[],"text":[{"type":"paragraph","text":"本报讯　上海市第七届人代会第三次会议主席团昨天下午举行首次会议。"},{"type":"paragraph","text":"陈国栋同志主持了会议。"},{"type":"paragraph","text":"会议推选陈国栋、胡立教、钟民、张承宗、狄景襄、苏步青、王涛、刘靖基、吴若安(女)、周谷城、李培南等十一人为主席团常务主席。"},{"type":"paragraph","text":"会议还通过了执行主席分组名单和会议日程，决定大会副秘书长人选和议案截止日期。"}]}