{"id":149936,"date":[{"year":1947,"month":5,"day":9}],"page":"4","source":"","region":"","masthead":"","special_issue":"","column":"街头闲话","genre":"","count":"160","ytitle":"","mtitle":"吃亏的是百姓","ftitle":"","authors":[],"text":[{"type":"paragraph","text":"生活指数解冻，是在必行了。物价呢，以一月份为例，到现在已经整整涨了三倍。——这就是政府雷厉风行实施“经济紧急措施方案”的全部结果。"},{"type":"paragraph","text":"剩下来的，大极是人不知鬼不觉，“方案”本身的无形解冻了。"},{"type":"paragraph","text":"现在官家的许多措施，“等因奉此”，都可作如是观。而归根结蒂，吃面的总是百姓。"},{"type":"paragraph","text":"好在百姓吃面，政府从来不必负什么责任。"}]}