{"id":1204494,"date":[{"year":1999,"month":6,"day":11}],"page":"5","source":"本报","region":"","masthead":"教育新闻·每日行情","special_issue":"","column":"","genre":"","count":"505","ytitle":"","mtitle":"扩大贷款范围　延长还款期限","ftitle":"浦东发展银行推出助学贷款新举措","authors":["李翔","杨昕"],"text":[{"type":"paragraph","text":"本报讯(记者李翔　实习生杨昕)　记者日前从上海浦东发展银行获悉，该行将扩大助学贷款的发放范围并延长还款期限，以方便更多的大学生贷款助学。贷款发放对象将从大学本、专科生扩大到研究生、定向代培生、自费生，学生毕业后还清贷款的期限也从原来的2年延长至4年。"},{"type":"paragraph","text":"浦发银行这次在助学贷款方面的新举措还有:全年随时受理学生的助学贷款申请，研究生每学年学费贷款最高限额可达2万元。学生在学期间可以随时部分或全部归还贷款本息；学生毕业后，按月额归还本息，贷款利率按照人民银行公布的一年期短期贷款利率执行。学生可以设法寻找一个或多个担保人，每个担保人最高可以承担3.5万元贷款的担保；学生也可以采用提供质押品或抵押物的方式进行担保。银行将缩短贷款审批时间，在资料和手续完备的前提下，做到15个工作日内予以批复，批复后3个工作日内贷款资金划转到位。"},{"type":"paragraph","text":"浦东发展银行是我国首家开办高校学生助学贷款业务的银行。两年来，该行与本市44所高校建立了对口服务关系，到今年4月底在上海地区已累计向1679名大学生发放助学贷款，其中学费贷款254万元，生活费贷款154万元。"}]}