{"id":598683,"date":[{"year":1980,"month":7,"day":24}],"page":"4","source":"","region":"","masthead":"","special_issue":"社会大学","column":"青年信箱","genre":"","count":"518","ytitle":"","mtitle":"刑满释放以后工龄如何计算?","ftitle":"","authors":["王贞韶"],"text":[{"type":"paragraph","text":"编辑同志:"},{"type":"paragraph","text":"我原是个青年学生，因偷窃一案为人民法院判处有期徒刑三年，并送某农场劳改，刑满释放，留场就业五年。去年初按政策回沪，经街道安排进厂工作。现在我要参加工会组织，须填写表格，为此请问，我的工龄如何计算?"},{"type":"paragraph","text":"彭林"},{"type":"paragraph","text":"彭林同志:"},{"type":"paragraph","text":"按照我国刑法，判处有期徒刑强迫劳动改造，乃是一种刑事处分。在服刑期间就是强迫改造，悔过自新，当然不可能有任何工龄可言，但在刑满释放安排就业后，应该按照党和政府的一贯劳动政策，和其他职工一样，从参加工作之日起计算连续工龄。"},{"type":"paragraph","text":"当然，受过刑事处分的各人情况并不一样，因此在工龄的具体计算上也不尽一样。例如，有的人在服刑以前已经参加工作，后来由于判刑而中断，他的工龄也因此中断，但可把那一段工作时间列为一般工龄，将来刑满就业，再从头计算连续工龄。而你，当时还只是一个青年学生，并未参加工作，就没有这个问题。你在劳改期满后安排在当地就业，现在又是经过本市有关部门同意，回上海安排工作的，其原在外地农场、企业的劳动或工作时间，完全有理由与现在劳动或工作时间合并在一起计算为连续工龄。具体地讲，你在刑满释放以后已经在当地工作了五年，去年调回上海又工作了一年，那么你的连续工龄则应为六年。"},{"type":"paragraph","text":"王贞韶"}]}