{"id":942635,"date":[{"year":1994,"month":5,"day":9}],"page":"5","source":"","region":"","masthead":"生活","special_issue":"生活","column":"国嘉·福安杯《名人轶事》征文,逝去的岁月","genre":"","count":"997","ytitle":"","mtitle":"会唱歌的四奶奶","ftitle":"","authors":["流星雨"],"text":[{"type":"paragraph","text":"流星雨"},{"type":"paragraph","text":"四奶奶不识字。"},{"type":"paragraph","text":"四奶奶会唱歌。"},{"type":"paragraph","text":"我第一次听四奶奶开口唱歌，是在十年前。那年的某天下午，村西的老柏树下很是热闹，很多人围在那里，还有人丢下田里的活往树下跑。我挤进人群才知道，有个瞎了眼的老妇人在唱歌，是个只要口饭吃不接受钱物的“卖唱者”。不知什么原因，四奶奶与瞎子对面坐着。我问旁人，旁人讲:对歌哩。"},{"type":"paragraph","text":"瞎子唱:手扶栏杆苦叹那第一声呐，亲爹爹做事实在不聪明哪……"},{"type":"paragraph","text":"四奶奶唱:手扶栏杆苦叹那第二声呐，可恨那亲娘实在不疼人哪……"},{"type":"paragraph","text":"瞎子唱:……。"},{"type":"paragraph","text":"四奶奶再唱:……。"},{"type":"paragraph","text":"没有琴弦，没有萧笛，也没有快板或者锁呐。两位老人一句交一句那么唱，像大柏树上那两只老鸟，晨暮里咕呀对语。"},{"type":"paragraph","text":"我问身边的二婶:唱么呢?"},{"type":"paragraph","text":"二婶撩起围裙角揩眼说:唱命呢。爹妈许配不依人，命苦。"},{"type":"paragraph","text":"我转头看瞎子，那混乎乎的眼里打转着泪水。四奶奶也有。"},{"type":"paragraph","text":"我不懂。只觉得心里有什么东西动了动。"},{"type":"paragraph","text":"瞎子打那以后，就成了我村人，住在四奶奶一个人住的家里。"},{"type":"paragraph","text":"那以后，四奶奶的小屋里常有歌声。我去听过几次，没看见四奶奶再挂泪。通常笑着，说寻着知音了呢。"},{"type":"paragraph","text":"我表姐出嫁头一天晚上，伯母请了四奶奶跟瞎子，说唱点喜庆。这天晚上为“劝女夜”，做爹妈的劝诫女儿过了门，要怎么孝敬公婆，该咋的照应丈夫，怎的与小姑叔弟相处……。分别前夜，多有凄情。那夜不同。表姐坐在厅堂中间，四奶奶和瞎子分坐两厢，一人头上还戴朵红绸子花，滑稽而好看。村人们里外围着。"},{"type":"paragraph","text":"四奶奶唱:一来忙，打开窗门亮煌煌；/二来忙，梳头净面落绣房；/三来忙，敬奉公婆捧茶汤；/四来忙，打扮姑叔进书房；/五来忙，丈夫出门整衣裳。"},{"type":"paragraph","text":"村人们中，有几个姑嫂跟着唱，汉子们以烟竿叩桌打着节拍，娃娃们摇头摆脚乱拍掌。唯有表姐红着脸，大气也不出。"},{"type":"paragraph","text":"瞎子接着唱:六来忙，姑娘出阁办嫁妆；/七来忙，催生满月做衣裳；/八来忙，讨个弟妇成成双；/九来忙，一串数珠进佛堂……"},{"type":"paragraph","text":"还有一个“十来忙，一双空手见阎王”，瞎子没唱，怕不吉利。"},{"type":"paragraph","text":"过了两年，瞎子病终。四奶奶让出给自己备着的楠木棺材，村人中几个壮力抬着“上山”了。"},{"type":"paragraph","text":"四奶奶跟着去。起坟后，坐在碑前，伊呀地说着什么。那声音，起先像哭，后来像唱。"},{"type":"paragraph","text":"坐在坟前的四奶奶，让我想起她第一次与瞎子面对面对歌的模样。"},{"type":"paragraph","text":"四奶奶不久也去了。人土时，用了只“四十九块五”(次等的松木棺材当时官价卖四十九块五角人民币，村人们便称之为“四十九块五”)。"},{"type":"paragraph","text":"“四十九块五”是村人和队上筹的。"}]}