{"id":538139,"date":[{"year":1974,"month":8,"day":17}],"page":"2","source":"新华社","region":"","masthead":"","special_issue":"","column":"批林批孔　把上层建筑领域的革命进行到底","genre":"","count":"123","ytitle":"","mtitle":"这是教师和学员一起交流学习马列著作和毛主席著作的体会","ftitle":"","authors":[],"text":[{"type":"paragraph","text":"<IMG alt=请插入6号盘，按F5键刷新后显示本插图！ src=\"D:\\inset\\1974\\08\\748h020401.JPG\">"},{"type":"paragraph","text":"<FONT class=imgsm>复旦大学政治理论课教研组举办哲学短训班，积极为基层单位深入批林批孔，培养马克思主义理论队伍。这是教师和学员一起交流学习马列著作和毛主席著作的体会。　新华社记者摄</FONT>"}]}