{"id":954983,"date":[{"year":1994,"month":9,"day":3}],"page":"2","source":"本报","region":"","masthead":"经济政治·社会新闻","special_issue":"","column":"特写","genre":"特写","count":"546","ytitle":"","mtitle":"长风伴月行　歌动蒙古包","ftitle":"","authors":["洪崇恩"],"text":[{"type":"paragraph","text":"夏日薄暮，玉兔东升。长风公园银锄湖旁，水气氲氤梧桐翠盖细柳袅娜处，新近出现了四座朱顶圆盘的蒙古包。此刻从蒙古包中传出了粗犷激越的赞歌，悠然飘扬，吸引着游园的人。"},{"type":"paragraph","text":"掀门低头，跨进一个中型的蒙古包。见地上一片绿毯，中央四根“乌尼”(柱子)，撑起包顶天庭，便感受到一种“风吹草低”“弯盖四方”的味道。几位着镶金大袍的蒙族姑娘在门边迎客，让座，敬酒、献茶，酒是一盅有“塞外茅台”之称的草原美酒宁城老窖，茶是一碗散发着丝丝膻味甜甜奶香的由马奶羊奶和砖茶混熬的茶。桌上有奶酪、奶豆腐、黄油、炒米等各种蒙古小点心，可以随意品尝。"},{"type":"paragraph","text":"蒙族好歌好舞。主办者为搞好这次“蒙古风情娱乐”，又特地从伊克昭盟选了一批能歌能舞的少男倩女来表演。蒙古包里响起了牧歌、《祝酒歌》、《赞歌》，跳起了《鄂尔多斯舞》，客人可以欣赏，可以和韵，也可以起而同舞。"},{"type":"paragraph","text":"夜探蒙古包，是长风公园最近推出的一系列新游乐活动之一。同时推出的还有世界名胜微缩景观展览等一批水陆节目。公园负责人蒋金城说:“养园经费不足是许多公园面临的共同困难。现在，我们从各地引进上述许多文化娱乐节目，既为上海市民增添了夏日消暑的好场所，也创造了一定的经济效益，这也是我们尝试自力更生解决经费短缺的一条新思路。”"},{"type":"paragraph","text":"本报记者　洪崇恩"}]}