{"id":678458,"date":[{"year":1984,"month":7,"day":14}],"page":"3","source":"","region":"","masthead":"","special_issue":"体育场(奥运会专刊)","column":"","genre":"","count":"156","ytitle":"","mtitle":"(1)吉姆·索普的孙子小比尔·索普和欧文斯的孙女吉纳·亨普希尔","ftitle":"","authors":[],"text":[{"type":"paragraph","text":"<IMG alt=请插入8号盘，按F5键刷新后显示本插图！ src=\"D:\\inset\\1984\\07\\847E030301.JPG\">"},{"type":"paragraph","text":"<FONT class=imgsm>①吉姆·索普的孙子小比尔·索普和欧文斯的孙女吉纳·亨普希尔。"},{"type":"paragraph","text":"②九十一岁的基维尔特在行进。"},{"type":"paragraph","text":"③美总统里根观看火炬传递。"},{"type":"paragraph","text":"④在希腊点燃奥林匹克圣火。"},{"type":"paragraph","text":"⑤美伤残运动员苏科夫斯基坐轮椅传递火炬。"},{"type":"paragraph","text":"⑥好奇的幼童围看火炬接力者。"},{"type":"paragraph","text":"⑦拳王阿里参加火炬接力。"},{"type":"paragraph","text":"(奥运会报道组编)</FONT>"}]}