{"id":300299,"date":[{"year":1954,"month":2,"day":19}],"page":"1","source":"本报","region":"","masthead":"","special_issue":"","column":"","genre":"","count":"1042","ytitle":"上海市推销建设公债工作全面展开","mtitle":"昨举行推销公债广播宣传大会","ftitle":"潘汉年同志作广播演讲号召全市人民完成本市预定任务","authors":[],"text":[{"type":"paragraph","text":"【本报讯】　本市推销一九五四年国家经济建设公债的工作，已全面展开。上海市推销一九五四年国家经济建设公债委员会和华东、上海人民广播电台在昨(十八)日下午六时半联合举行了推销一九五四年国家经济建设公债广播宣传大会。"},{"type":"paragraph","text":"在广播宣传大会上，首先播送了上海市推销一九五四年国家经济建设公债委员会主任委员潘汉年的广播演讲。潘汉年主任委员号召本市广大职工、市郊农民、私营工商业者和全上海的市民，更进一步发扬爱国热忱，积极拥护国家经济建设公债的发行，完成本市的预定推销任务，把我们祖国建设成为一个强大的、幸福的、繁荣的社会主义国家!(潘汉年主任委员讲演内容摘要见第四版)"},{"type":"paragraph","text":"接着，全国纺织工业劳动模范裔式娟、上海市工商业联合会副主任委员荣毅仁、卢湾区人民代表、里弄妇女王淑霞分别讲话。他们一致表示响应潘汉年主任委员的号召，踊跃购买经济建设公债。荣毅仁说:踊跃认购公债，是私营工商业者拥护国家在过渡时期总路线和爱国的具体表现之一，几年来，私营工商业在国家领导与扶助下，都有不同程度的发展，并都获得合理利润。因此，私营工商业者拿出一部分钱来帮助国家的社会主义工业化建设是完全应该与必要的。同时，私营工商业者拥有不少游资，这些游资决不应该拿来做破坏国计民生的投机活动，而应该拿来做有益于国计民生的事情，购买公债就是这类事情的一种。他说:今后，我们私营工商业者一方面要积极地接受社会主义改造，同时要抓住这次认购国家经济建设公债的机会，为国家建设多尽一分力量。裔式娟同志热情地说:当我晓得:我们国家要发行建设公债的消息后，心里非常高兴。因为，我又多了一个好机会，可以在支援国家社会主义建设事业中，多出一份力量。为了国家的社会主义工业化，我们工人在增产节约运动中起了模范作用，为国家增加财富、积累了资金；今天在国家发行经济建设公债的时候，我们工人还要带头购买公债，推动各界人民，进一步来支援国家的社会主义工业化建设。里弄妇女王淑霞说:解放以前，我一家愁吃愁穿，现在，我家不但能够维持生活，每月还有些多余，我们全家都表示要把这笔多余的钱来购买经济建设公债，支援国家的社会主义建设，国家建设好了，我们的幸福生活也就更有保障，我们的下一代的生活也将更加幸福。"},{"type":"paragraph","text":"在广播宣传大会进行中，沪剧演员丁是娥、越剧演员金采风、吕瑞英、赵雅麟、评弹演员蒋月泉、京剧演员李玉茹、陈大濩和歌唱家蔡绍序等表演了文艺节目。广播宣传大会至八时半结束。"}]}